eliminate_newlines/__init__.py
eliminate_newlines/__main__.py
eliminate_newlines/cli.py
eliminate_newlines/core.py
eliminate_newlines-1.2.dist-info/LICENSE
eliminate_newlines-1.2.dist-info/METADATA
eliminate_newlines-1.2.dist-info/WHEEL
eliminate_newlines-1.2.dist-info/entry_points.txt
eliminate_newlines-1.2.dist-info/top_level.txt
eliminate_newlines-1.2.dist-info/RECORD
