Metadata-Version: 2.1
Name: eliminate-newlines
Version: 1.2
Summary: CLI that formats Python code in such a way that after the function definition header all newlines will be deleted
Home-page: https://github.com/PatrikHlobil/Eliminate-Newlines-After-Function-Definition
Author: Patrik Hlobil
Author-email: patrik.hlobil@googlemail.com
License: UNKNOWN
Platform: UNKNOWN
Classifier: Programming Language :: Python :: 3.6
Classifier: Programming Language :: Python :: 3.7
Classifier: Programming Language :: Python :: 3.8
Classifier: License :: OSI Approved :: MIT License
Classifier: Operating System :: OS Independent
Requires-Python: >=3.6
Requires-Dist: click (>=7.1.2)
Requires-Dist: colorama (>=0.4.3)
